{
 "standings": [
  {
   "lastAccept": 1589885514,
   "pos": 1,
   "score": 2474,
   "taskStats": {
    "test": {
     "points": 500,
     "time": 1589882878
    },
    "test10": {
     "points": 500,
     "time": 1589882243
    },
    "test2": {
     "points": 474,
     "time": 1589882551
    },
    "test4": {
     "points": 500,
     "time": 1589885180
    },
    "test5": {
     "points": 500,
     "time": 1589885514
    }
   },
   "team": "Testando"
  },
  {
   "lastAccept": 1589855366,
   "pos": 2,
   "score": 474,
   "taskStats": {
    "test2": {
     "points": 474,
     "time": 1589855366
    }
   },
   "team": "Tua m\u00e3e, aquela ursa"
  }
 ],
 "tasks": [
  "test2",
  "test10",
  "test",
  "test4",
  "test5"
 ]
}